taskcond/__init__.py
taskcond/cli.py
taskcond/py.typed
taskcond/core/__init__.py
taskcond/core/manager.py
taskcond/core/orchestrator.py
taskcond/core/task.py
taskcond-0.2.1.dist-info/licenses/LICENSE
taskcond-0.2.1.dist-info/METADATA
taskcond-0.2.1.dist-info/WHEEL
taskcond-0.2.1.dist-info/entry_points.txt
taskcond-0.2.1.dist-info/top_level.txt
taskcond-0.2.1.dist-info/RECORD
