Metadata-Version: 2.4
Name: taskcond
Version: 0.2.1
Summary: pythonic task runner.
Author: moray21
License: MIT License
Classifier: Programming Language :: Python :: 3.11
Classifier: Programming Language :: Python :: 3.12
Classifier: Programming Language :: Python :: 3.13
Requires-Python: >=3.11
License-File: LICENSE
Requires-Dist: tqdm
Provides-Extra: develop
Requires-Dist: pytest; extra == "develop"
Requires-Dist: coverage; extra == "develop"
Requires-Dist: flake8; extra == "develop"
Requires-Dist: mypy; extra == "develop"
Requires-Dist: black; extra == "develop"
Requires-Dist: isort; extra == "develop"
Requires-Dist: types-tqdm; extra == "develop"
Requires-Dist: build; extra == "develop"
Requires-Dist: twine; extra == "develop"
Dynamic: license-file
